repomaestro/__init__.py
repomaestro/config.py
repomaestro/logger.py
repomaestro/platform/__init__.py
repomaestro/platform/github.py
repomaestro-2.0.0.dist-info/LICENSE
repomaestro-2.0.0.dist-info/METADATA
repomaestro-2.0.0.dist-info/WHEEL
repomaestro-2.0.0.dist-info/entry_points.txt
repomaestro-2.0.0.dist-info/RECORD
