Metadata-Version: 2.1
Name: repomaestro
Version: 2.0.0
Summary: Code repositories conductor
Home-page: https://github.com/cliffano/repomaestro
License: Apache-2.0
Keywords: repomaestro,...
Author: Cliffano Subagio
Author-email: cliffano@gmail.com
Requires-Python: >=3.11,<4.0
Classifier: License :: OSI Approved :: Apache Software License
Classifier: Operating System :: OS Independent
Classifier: Programming Language :: Python :: 3
Classifier: Programming Language :: Python :: 3.11
Classifier: Programming Language :: Python :: 3.12
Classifier: Programming Language :: Python :: 3.13
Requires-Dist: Jinja2 (>=3.1.6,<4.0.0)
Requires-Dist: PyGithub (>=2.6.1,<3.0.0)
Requires-Dist: PyYAML (>=6.0.2,<7.0.0)
Requires-Dist: click (>=8.1.8,<9.0.0)
Requires-Dist: conflog (>=2.0.1,<3.0.0)
Project-URL: Documentation, https://github.com/cliffano/repomaestro
Project-URL: Repository, https://github.com/cliffano/repomaestro
